{
  "timestamp": "20260406_135659",
  "duration_seconds": 0.046541,
  "original_features": 12,
  "enriched_features": 45,
  "added_features": 33,
  "new_features": [
    "nilsson_omega",
    "BE_per_A",
    "N_magic_dist",
    "Q0_intrinsic",
    "deformation_type",
    "Beta_2_estimated",
    "BE_asymmetry",
    "Z_magic_dist",
    "vib_frequency",
    "nuclear_radius",
    "Z_shell_gap",
    "N_shell_gap",
    "ws_surface_thick",
    "moment_of_inertia",
    "N_nearest_magic",
    "S_n_approx",
    "fermi_energy",
    "BE_pairing",
    "BE_volume",
    "BE_total",
    "N_valence",
    "E_2plus",
    "nilsson_epsilon",
    "is_singly_magic",
    "Z_valence",
    "nucleus_collective_type",
    "BE_coulomb",
    "S_p_approx",
    "is_doubly_magic",
    "BE_surface",
    "Z_nearest_magic",
    "rotational_param",
    "magic_character"
  ],
  "calculations_done": {
    "semf": true,
    "shell_model": true,
    "woods_saxon": true,
    "nilsson": true,
    "collective": true,
    "schmidt": true,
    "deformation": true
  },
  "sample_statistics": {
    "BE_per_A_mean": 8.093569014396993,
    "magic_character_mean": 0.1046128374174291,
    "doubly_magic_count": 0
  }
}